bayesfit/__init__.py
bayesfit/applyPriors.py
bayesfit/bayesfit.py
bayesfit/calc_integral.py
bayesfit/checkData.py
bayesfit/checkLogspace.py
bayesfit/checkOptions.py
bayesfit/checkParams.py
bayesfit/checkPriors.py
bayesfit/demo_01.py
bayesfit/extractMetrics.py
bayesfit/extractPriors.py
bayesfit/genGrid.py
bayesfit/get_Threshold.py
bayesfit/gridLikelihood.py
bayesfit/plot_Marginals.py
bayesfit/plot_Posterior.py
bayesfit/plot_Priors.py
bayesfit/plot_psyFcn.py
bayesfit/psyFunction.py
bayesfit/test_bayesFit.py
bayesfit/test_checkData.py
bayesfit/test_checkLogspace.py
bayesfit/test_checkOptions.py
bayesfit/test_checkParams_constraints.py
bayesfit/test_checkParams_param_ests.py
bayesfit/test_checkPriors.py
bayesfit/test_extractPriors.py
bayesfit/test_plots.py
bayesfit/test_travis.py
bayesfit-2.4.dist-info/LICENSE.txt
bayesfit-2.4.dist-info/METADATA
bayesfit-2.4.dist-info/WHEEL
bayesfit-2.4.dist-info/top_level.txt
bayesfit-2.4.dist-info/RECORD
